protobuf_decoder/__init__.py
protobuf_decoder/protobuf_decoder.py
protobuf_decoder-0.4.0.dist-info/LICENSE
protobuf_decoder-0.4.0.dist-info/METADATA
protobuf_decoder-0.4.0.dist-info/WHEEL
protobuf_decoder-0.4.0.dist-info/top_level.txt
protobuf_decoder-0.4.0.dist-info/RECORD
