Metadata-Version: 2.1
Name: protobuf_decoder
Version: 0.4.0
Summary: Decode protobuf without proto file
Home-page: https://github.com/dannyhann/protobuf_decoder
Author: danny han
Author-email: rhrnak0501@gmail.com
License: UNKNOWN
Platform: UNKNOWN
Classifier: Programming Language :: Python :: 3
Classifier: License :: OSI Approved :: MIT License
Classifier: Operating System :: OS Independent
Requires-Python: >=3.7
License-File: LICENSE
